RL2/__init__.py
RL2/datasets/__init__.py
RL2/datasets/base.py
RL2/datasets/dpo.py
RL2/datasets/rl.py
RL2/datasets/rm.py
RL2/datasets/sft.py
RL2/trainer/__init__.py
RL2/trainer/base.py
RL2/trainer/dpo.py
RL2/trainer/ppo.py
RL2/trainer/rm.py
RL2/trainer/sft.py
RL2/trainer/config/dpo.yaml
RL2/trainer/config/ppo.yaml
RL2/trainer/config/rm.yaml
RL2/trainer/config/sft.yaml
RL2/utils/__init__.py
RL2/utils/algorithms.py
RL2/utils/checkpointing.py
RL2/utils/comm.py
RL2/utils/data_parallelism.py
RL2/utils/functions.py
RL2/utils/logging.py
RL2/utils/offloading.py
RL2/utils/seqlen_balance.py
RL2/utils/sequence_parallelism.py
RL2/utils/sequences.py
RL2/utils/sglang.py
RL2/utils/tensor_parallelism.py
RL2/workers/__init__.py
RL2/workers/actor.py
RL2/workers/base.py
RL2/workers/critic.py
RL2/workers/rollout.py
rl_square-0.0.2.dist-info/licenses/LICENSE
rl_square-0.0.2.dist-info/licenses/NOTICE
rl_square-0.0.2.dist-info/METADATA
rl_square-0.0.2.dist-info/WHEEL
rl_square-0.0.2.dist-info/top_level.txt
rl_square-0.0.2.dist-info/RECORD
