Metadata-Version: 2.4
Name: rl-square
Version: 0.0.2
Summary: RL2: Ray Less Reinforcement Learning
Home-page: https://github.com/ChenmienTan/RL2
Author: Chenmien Tan, Simon Yu, Lanbo Lin, Ze Zhang, Yuanwu Xu, Chenhao Jiang, Tianyuan Yang, Sicong Xie, Guannan Zhang
Author-email: chenmientan@outlook.com
Requires-Python: >=3.10
License-File: LICENSE
License-File: NOTICE
Requires-Dist: hydra-core
Requires-Dist: ninja
Requires-Dist: ring-flash-attn==0.1.8
Requires-Dist: torch==2.8.0
Requires-Dist: tqdm
Requires-Dist: transformers
Requires-Dist: peft
Requires-Dist: liger_kernel
Requires-Dist: sglang[all]==0.5.2
Requires-Dist: wandb
Requires-Dist: flash-attn==2.8.3
Requires-Dist: torchdata
Dynamic: author
Dynamic: author-email
Dynamic: description
Dynamic: description-content-type
Dynamic: home-page
Dynamic: license-file
Dynamic: requires-dist
Dynamic: requires-python
Dynamic: summary
